devo/__init__.py
devo/__version__.py
devo/api/__init__.py
devo/api/client.py
devo/api/processors.py
devo/api/scripts/__init__.py
devo/api/scripts/client_cli.py
devo/common/__init__.py
devo/common/dates/__init__.py
devo/common/dates/dateoperations.py
devo/common/dates/dateparser.py
devo/common/dates/dateutils.py
devo/common/generic/__init__.py
devo/common/generic/configuration.py
devo/common/loadenv/__init__.py
devo/common/loadenv/load_env.py
devo/common/logging/__init__.py
devo/common/logging/log.py
devo/sender/__init__.py
devo/sender/data.py
devo/sender/lookup.py
devo/sender/pfx_to_pem.py
devo/sender/transformsyslog.py
devo/sender/scripts/__init__.py
devo/sender/scripts/sender_cli.py
devo_sdk-6.0.6.dist-info/licenses/LICENSE
devo_sdk-6.0.6.dist-info/METADATA
devo_sdk-6.0.6.dist-info/WHEEL
devo_sdk-6.0.6.dist-info/entry_points.txt
devo_sdk-6.0.6.dist-info/top_level.txt
devo_sdk-6.0.6.dist-info/RECORD
