Metadata-Version: 2.4
Name: devo-sdk
Version: 6.0.6
Summary: Devo Software Development Kit for Python.
Home-page: https://github.com/DevoInc/python-sdk
Author: Devo, Inc.
Author-email: support@devo.com
License: MIT
Classifier: Programming Language :: Python
Classifier: Development Status :: 5 - Production/Stable
Classifier: Intended Audience :: Developers
Classifier: Natural Language :: English
Classifier: License :: OSI Approved :: MIT License
Classifier: Operating System :: OS Independent
Classifier: Programming Language :: Python
Classifier: Programming Language :: Python :: 3
Classifier: Programming Language :: Python :: 3.9
Classifier: Programming Language :: Python :: 3.10
Classifier: Programming Language :: Python :: 3.11
Classifier: Programming Language :: Python :: 3.12
Classifier: Programming Language :: Python :: 3.13
Classifier: Programming Language :: Python :: Implementation :: CPython
Classifier: Programming Language :: Python :: Implementation :: PyPy
Classifier: Topic :: Software Development :: Libraries :: Python Modules
License-File: LICENSE
Requires-Dist: requests~=2.32
Requires-Dist: click==8.1.8
Requires-Dist: PyYAML~=6.0.1
Requires-Dist: pem~=21.2.0
Requires-Dist: pyopenssl~=25.0.0
Requires-Dist: pytz~=2024.1
Requires-Dist: certifi~=2025.1.31
Requires-Dist: cryptography~=44.0.0
Provides-Extra: dev
Requires-Dist: msgpack~=1.0.8; extra == "dev"
Requires-Dist: responses~=0.25.3; extra == "dev"
Requires-Dist: pipdeptree~=2.23.0; extra == "dev"
Requires-Dist: pytest~=8.2.2; extra == "dev"
Requires-Dist: pytest-cov~=5.0.0; extra == "dev"
Requires-Dist: mock~=5.1.0; extra == "dev"
Requires-Dist: pebble~=5.0.7; extra == "dev"
Dynamic: author
Dynamic: author-email
Dynamic: classifier
Dynamic: description
Dynamic: description-content-type
Dynamic: home-page
Dynamic: license
Dynamic: license-file
Dynamic: provides-extra
Dynamic: requires-dist
Dynamic: summary
